{
    "neoforge:conditions":  [
                                {
                                    "type":  "neoforge:mod_loaded",
                                    "modid":  "tfc_items"
                                }
                            ],
    "type":  "tfc:heating",
    "ingredient":  {
                       "tag":  "c:wires/tungsten"
                   },
    "result_fluid":  {
                         "amount":  25,
                         "id":  "tfc:metal/tungsten"
                     },
    "temperature":  1535
}
